pigui/__init__.py
pigui/buttons.py
pigui/colors.py
pigui/container.py
pigui/events.py
pigui/input.py
pigui/labels.py
pigui/widgets.py
pigUI-1.0.4a0.dist-info/LICENSE
pigUI-1.0.4a0.dist-info/METADATA
pigUI-1.0.4a0.dist-info/WHEEL
pigUI-1.0.4a0.dist-info/top_level.txt
pigUI-1.0.4a0.dist-info/RECORD
