Metadata-Version: 2.1
Name: pigUI
Version: 1.0.4a0
Summary: UNKNOWN
Home-page: https://github.com/s0lst1ce/pigUI
Author: s0lst1ce
License: UNKNOWN
Platform: UNKNOWN
Classifier: Programming Language :: Python :: 3
Classifier: Development Status :: 3 - Alpha
Classifier: License :: OSI Approved :: GNU General Public License v3 (GPLv3)
Classifier: Operating System :: OS Independent
Requires-Python: >=3.7
Requires-Dist: pygame (>=2.0.0.dev3)
